interpals_api/__init__.py
interpals_api/api.py
interpals_api/cookie.py
interpals_api/errors.py
interpals_api/session.py
interpals_api/utils.py
interpals_api/parsers/__init__.py
interpals_api/parsers/chat_parser.py
interpals_api/parsers/friends_parser.py
interpals_api/parsers/pictures_parser.py
interpals_api/parsers/profile_parser.py
interpals_api-2.3.1.dist-info/METADATA
interpals_api-2.3.1.dist-info/WHEEL
interpals_api-2.3.1.dist-info/top_level.txt
interpals_api-2.3.1.dist-info/RECORD
