Metadata-Version: 2.4
Name: interpals-api
Version: 2.3.1
Summary: Unofficial Python API for Interpals.net.
Home-page: https://github.com/fomalhaut88/interpals-api
Author: Alexander Khlebushchev
License: MIT
Project-URL: Homepage, https://pypi.org/project/interpals-api/
Project-URL: Documentation, https://fomalhaut88.github.io/interpals-api/
Project-URL: Source, https://github.com/fomalhaut88/interpals-api
Project-URL: Issues, https://github.com/fomalhaut88/interpals-api/issues
Classifier: Development Status :: 5 - Production/Stable
Classifier: Intended Audience :: Developers
Classifier: Topic :: Internet :: WWW/HTTP
Classifier: Topic :: Software Development :: Libraries :: Python Modules
Classifier: License :: OSI Approved :: MIT License
Classifier: Programming Language :: Python :: 3.12
Classifier: Operating System :: OS Independent
Requires-Python: >=3.12
Requires-Dist: aiohttp>=3.12
Requires-Dist: requests>=2.32
Requires-Dist: lxml>=6.0
Requires-Dist: beautifulsoup4>=4.13
Dynamic: author
Dynamic: classifier
Dynamic: description
Dynamic: description-content-type
Dynamic: home-page
Dynamic: license
Dynamic: project-url
Dynamic: requires-dist
Dynamic: requires-python
Dynamic: summary
